app_pkg/__init__.py
app_pkg/scripts/__init__.py
app_pkg/scripts/sweatygoals.py
sweatygoals/__init__.py
sweatygoals/scripts/__init__.py
sweatygoals/scripts/sweatygoals.py
sweatygoals-0.12.dist-info/LICENSE
sweatygoals-0.12.dist-info/METADATA
sweatygoals-0.12.dist-info/WHEEL
sweatygoals-0.12.dist-info/entry_points.txt
sweatygoals-0.12.dist-info/top_level.txt
sweatygoals-0.12.dist-info/RECORD
