Metadata-Version: 2.1
Name: sweatygoals
Version: 0.12
Summary: A CLI tool that retrieves latest football matches
Home-page: https://github.com/AndresXI/sweaty-goals
Author: Andres Alcocer
Author-email: andresalcocer7@yahoo.com
License: UNKNOWN
Platform: UNKNOWN
Requires-Dist: Click
Requires-Dist: Requests
Requires-Dist: Python-dateutil
